setup.py
36ban/__init__.py
36ban_commons.egg-info/PKG-INFO
36ban_commons.egg-info/SOURCES.txt
36ban_commons.egg-info/dependency_links.txt
36ban_commons.egg-info/top_level.txt
generate/__init__.py
generate/application.py
generate/generate_code_service.py